django_purchase_ve-0.1.0.dist-info/licenses/LICENSE
purchase/__init__.py
purchase/apps.py
purchase/conf.py
purchase/enums.py
purchase/api/serializers.py
purchase/api/urls.py
purchase/api/views.py
purchase/mgmt/commands/purchase_bootstrap_demo.py
purchase/migrations/0001_initial.py
purchase/models/config.py
purchase/models/doc_bill.py
purchase/models/doc_payment.py
purchase/models/doc_vendorcredit.py
purchase/models/item.py
purchase/models/party.py
purchase/models/tax.py
purchase/posting/adapters.py
purchase/posting/signals.py
purchase/tests/conftest.py
purchase/tests/test_bill_posting.py
purchase/tests/test_payment_refund_posting.py
purchase/tests/test_vendorcredit_posting.py
purchase/utils/money.py
purchase/utils/tax.py
django_purchase_ve-0.1.0.dist-info/METADATA
django_purchase_ve-0.1.0.dist-info/WHEEL
django_purchase_ve-0.1.0.dist-info/top_level.txt
django_purchase_ve-0.1.0.dist-info/RECORD
